[
  {
    "code": "de",
    "name": "German"
  },
  {
    "code": "hi",
    "name": "Hindi"
  },
  {
    "code": "ru",
    "name": "Russian"
  },
  {
    "code": "uz-lat",
    "name": "Uzbek (latin)"
  },
  {
    "code": "fr",
    "name": "French"
  },
  {
    "code": "ua",
    "name": "Ukrainian"
  },
  {
    "code": "zh-cn",
    "name": "Chinese (Simplified)"
  },
  {
    "code": "hu",
    "name": "Hungarian"
  },
  {
    "code": "hy",
    "name": "Armenian"
  },
  {
    "code": "sk",
    "name": "Slovak"
  },
  {
    "code": "id",
    "name": "Indonesian"
  },
  {
    "code": "ca",
    "name": "Catalan"
  },
  {
    "code": "sr",
    "name": "Serbian"
  },
  {
    "code": "ar-ly",
    "name": "Arabic (Libya)"
  },
  {
    "code": "sv",
    "name": "Swedish"
  },
  {
    "code": "ko",
    "name": "Korean"
  },
  {
    "code": "zh-tw",
    "name": "Chinese (Traditional)"
  },
  {
    "code": "gl",
    "name": "Galician"
  },
  {
    "code": "mr",
    "name": "Marathi"
  },
  {
    "code": "my",
    "name": "Myanmar"
  },  
  {
    "code": "pt-br",
    "name": "Portuguese (Brazilian)"
  },
  {
    "code": "el",
    "name": "Greek"
  },
  {
    "code": "en",
    "name": "English"
  },
  {
    "code": "it",
    "name": "Italian"
  },
  {
    "code": "ta",
    "name": "Tamil"
  },
  {
    "code": "es",
    "name": "Spanish"
  },
  {
    "code": "et",
    "name": "Estonian"
  },
  {
    "code": "cs",
    "name": "Czech"
  },
  {
    "code": "pt-pt",
    "name": "Portuguese"
  },
  {
    "code": "vi",
    "name": "Vietnamese"
  },
  {
    "code": "th",
    "name": "Thai"
  },
  {
    "code": "ja",
    "name": "Japanese"
  },
  {
    "code": "fa",
    "name": "Farsi"
  },
  {
    "code": "pl",
    "name": "Polish"
  },
  {
    "code": "da",
    "name": "Danish"
  },
  {
    "code": "ro",
    "name": "Romanian"
  },
  {
    "code": "nl",
    "name": "Dutch"
  },
  {
    "code": "tr",
    "name": "Turkish"
  }
]